tp2/TP2_ISL/LFSR/design.sv
module LFSR (
    input clk,        // Clock
    input rst_n,      // Reset (ativo em nível baixo)
    output reg [3:0] lfsr // LFSR de 4 bits
);

    // Inicializa o LFSR
    initial begin
        lfsr = 4'b0001; // Valor inicial
    end

    // Desloca o LFSR a cada borda positiva do clock
    always @(posedge clk or negedge rst_n) begin
        if (!rst_n)
            lfsr <= 4'b0001; // Reseta o LFSR
        else
          	lfsr <= {lfsr[2:0], lfsr[3] ^ lfsr[0]}; // Desloca e aplica feedback
    end
endmodule

tp2/TP2_ISL/LFSR/testbench.sv
// Testbench para o módulo LFSR
module tb_LFSR;
    reg clk;                          // Sinal de clock para o teste
    reg rst_n;                        // Sinal de reset ativo em nível baixo
    wire [3:0] lfsr;                  // Saída do LFSR a ser monitorada

    // Instância do módulo LFSR
    LFSR uut (
        .clk(clk),
        .rst_n(rst_n),
        .lfsr(lfsr)
    );

    // Gera o clock
    initial begin
        clk = 0;
        forever #5 clk = ~clk; // Clock com período de 10 unidades de tempo
    end

    // Testa o LFSR
    initial begin
        // Configura o arquivo VCD para dumping
        $dumpfile("lfsr_dump.vcd");  // Nome do arquivo VCD
        $dumpvars(0, tb_LFSR);       // Salva todas as variáveis do testbench

        // Inicializa o sinal de reset
        rst_n = 0;                   // Ativa o reset (ativo em nível baixo)
        #10;                         // Aguarda para garantir que o LFSR esteja inicializado

        // Desativa o reset e aguarda para observar o comportamento
        rst_n = 1;
        #100;                        // Tempo para observar o comportamento do LFSR

        // Finaliza a simulação
        $finish;
    end

    // Monitoramento
    initial begin
        $monitor("Tempo = %0t | LFSR = %b", $time, lfsr);
    end
endmodule

tp2/TP2_ISL/LFSR/lfsr_dump.vcd
$date
	Tue Aug 13 07:27:46 2024
$end
$version
	Icarus Verilog
$end
$timescale
	1s
$end
$scope module tb_LFSR $end
$var wire 4 ! lfsr [3:0] $end
$var reg 1 " clk $end
$var reg 1 # rst_n $end
$scope module uut $end
$var wire 1 " clk $end
$var wire 1 # rst_n $end
$var reg 4 $ lfsr [3:0] $end
$upscope $end
$upscope $end
$enddefinitions $end
$comment Show the parameter values. $end
$dumpall
$end
#0
$dumpvars
b1 $
0#
0"
b1 !
$end
#5
1"
#10
0"
1#
#15
b11 !
b11 $
1"
#20
0"
#25
b111 !
b111 $
1"
#30
0"
#35
b1111 !
b1111 $
1"
#40
0"
#45
b1110 !
b1110 $
1"
#50
0"
#55
b1101 !
b1101 $
1"
#60
0"
#65
b1010 !
b1010 $
1"
#70
0"
#75
b101 !
b101 $
1"
#80
0"
#85
b1011 !
b1011 $
1"
#90
0"
#95
b110 !
b110 $
1"
#100
0"
#105
b1100 !
b1100 $
1"
